transport/__init__.py
transport/ble.py
transport/tcp.py
transport/uart.py
mindstorms_net-0.1.0.dist-info/METADATA
mindstorms_net-0.1.0.dist-info/WHEEL
mindstorms_net-0.1.0.dist-info/top_level.txt
mindstorms_net-0.1.0.dist-info/RECORD
