Metadata-Version: 2.4
Name: mindstorms-net
Version: 0.1.0
Summary: Python package to connect LEGO EV3 and 51515 via ESP32/BLE/serial
Home-page: https://github.com/yourusername/mindstorms-net
Author: Your Name
Author-email: youremail@example.com
Classifier: Programming Language :: Python :: 3
Classifier: License :: OSI Approved :: MIT License
Classifier: Operating System :: OS Independent
Requires-Python: >=3.5
Dynamic: author
Dynamic: author-email
Dynamic: classifier
Dynamic: description
Dynamic: description-content-type
Dynamic: home-page
Dynamic: requires-python
Dynamic: summary
